{
  "kind": "public_corpus_api_releases",
  "releases": [
    {
      "slug": "chemistry-record-auditor-tool",
      "path": "results/chemistry-record-auditor-tool",
      "status": "autopublished",
      "pushed": true
    },
    {
      "slug": "chemistry-record-auditor-tool-v2",
      "path": "results/chemistry-record-auditor-tool-v2",
      "status": "autopublished",
      "pushed": true
    },
    {
      "slug": "chemistry-record-auditor-tool-v2-v2",
      "path": "results/chemistry-record-auditor-tool-v2-v2",
      "status": "autopublished",
      "pushed": true
    },
    {
      "slug": "corpus-deduplication",
      "path": "results/corpus-deduplication",
      "status": "autopublished",
      "pushed": false
    },
    {
      "slug": "energy-usage-anomaly-auditor",
      "path": "results/energy-usage-anomaly-auditor",
      "status": "autopublished",
      "pushed": true
    },
    {
      "slug": "energy-usage-anomaly-auditor-v2",
      "path": "results/energy-usage-anomaly-auditor-v2",
      "status": "autopublished",
      "pushed": true
    },
    {
      "slug": "evidence-chain",
      "path": "results/evidence-chain",
      "status": "autopublished",
      "pushed": false
    },
    {
      "slug": "evidence-chain-v2",
      "path": "results/evidence-chain-v2",
      "status": "autopublished",
      "pushed": true
    },
    {
      "slug": "patch-risk-auditor",
      "path": "results/patch-risk-auditor",
      "status": "autopublished",
      "pushed": true
    },
    {
      "slug": "patch-risk-auditor-v2",
      "path": "results/patch-risk-auditor-v2",
      "status": "autopublished",
      "pushed": true
    },
    {
      "slug": "toolchain-policy",
      "path": "results/toolchain-policy",
      "status": "autopublished",
      "pushed": false
    }
  ],
  "evidenceHash": "3e254f9001f96eee967b48ee8778ea22d3a9699a83f0ba8be0db13594a523e28"
}
