{
  "kind": "conceptual_principle_audit_wave_summary",
  "slug": "batch138-conceptual-principle-audit-wave",
  "title": "Batch 138 Conceptual Principle Audit Wave",
  "resultKind": "conceptual_principle_audit_wave",
  "qualityLabel": "good",
  "candidateStatus": "autopublished",
  "lifecycleStatus": "autopublished",
  "releaseReadinessScore": 88,
  "evidenceStrengthScore": 86,
  "reproducibilityScore": 91,
  "publicationSafetyScore": 99,
  "replayCriticalPassRate": 100,
  "specificityScore": 94,
  "antiTemplateStatus": "specific_public_evidence",
  "publicHygienePassed": true,
  "safetyScanPassed": true,
  "reliabilityReplayPassed": true,
  "falsificationStatus": "passes_falsification",
  "baselineComparisonPresent": true,
  "scientificMemoryUpdated": true,
  "scientificQuestion": "Can Field-Bound Claim Safety support receipt-backed external scientific and technical claim review at scale?",
  "domain": "external review scientist hard mode",
  "phase": "Phase 2 Heavy External Audit Waves",
  "objective": "Conceptual principle audit wave",
  "limitations": [
    "Bounded safe computational evidence only.",
    "Claim labels are review decisions, not proof.",
    "No outside-party uptake or broad maturity claim is made."
  ],
  "principleClaimsAudited": 10,
  "evidenceChecks": 5,
  "nonExamples": 5,
  "rivalExplanations": 4,
  "evidenceHash": "96aa0e2548222940b5b70f092dcd3d8da2d81b48c0bf5be0736191ce3f00b660"
}
