{
  "slug": "batch52-conceptual-discovery-paper",
  "resultKind": "conceptual_discovery_paper",
  "qualityLabel": "good",
  "candidateStatus": "autopublished",
  "releaseReadinessScore": 91,
  "evidenceStrengthScore": 90,
  "reproducibilityScore": 88,
  "publicationSafetyScore": 99,
  "replayCriticalPassRate": 100,
  "specificityScore": 94,
  "antiTemplateStatus": "specific_public_evidence",
  "publicHygienePassed": true,
  "safetyScanPassed": true,
  "reliabilityReplayPassed": true,
  "kind": "autopublish_record",
  "pushed": true
}
