{
  "kind": "public_corpus_result_badges",
  "slug": "route-stage04-routing-policy-calibration",
  "badges": {
    "quality": "good",
    "status": "autopublished",
    "antiTemplate": "specific_public_evidence",
    "replay": "replay-100",
    "safety": "safety-passed",
    "hygiene": "hygiene-passed",
    "worker": "not-recorded",
    "falsification": "passes_falsification",
    "lifecycle": "autopublished",
    "version": "route-stage04-routing-policy-calibration",
    "showcase": "not-showcase"
  },
  "lifecycleStatus": "autopublished",
  "showcaseRank": null,
  "evidenceHash": "3eee88f6c9e38b0fb1c7fab43f30dbf32deec2798a52ff25a2f7d718f0eddd6f"
}
