{
  "kind": "os15_target_receipt",
  "receiptId": "receipt-os15-target-0178",
  "targetId": "os15-target-0178",
  "targetClass": "formal_counterexample",
  "route": "formal_counterexample",
  "status": "executed",
  "sourceUrl": "https://example.org/os15/formal_counterexample/178",
  "retrievalMethod": "public_metadata_route_receipt",
  "executed": true,
  "executionAttemptType": "bounded_formal_check",
  "evidenceChecks": [
    "evidence-os15-target-0178-01",
    "evidence-os15-target-0178-02",
    "evidence-os15-target-0178-03",
    "evidence-os15-target-0178-04",
    "evidence-os15-target-0178-05",
    "evidence-os15-target-0178-06"
  ],
  "timeToEvidenceMinutes": 13.2,
  "noRawLogs": true,
  "noLocalPaths": true,
  "noFakeTargetExecution": true,
  "caveats": [
    "bounded public-target receipt; not outside validation"
  ],
  "evidenceHash": "118c13ecf6159648ace094d7ca4812f7a82562d2e5421f34ee0e580644376c48"
}
