{
  "resultId": "patch-risk-auditor",
  "slug": "patch-risk-auditor-v2",
  "title": "Patch Risk Auditor",
  "sourceType": "pilot",
  "sourceId": "patch-risk-auditor",
  "publishedBy": "sovryn-autopublish",
  "humanReviewRequired": false,
  "automatedPolicyVersion": "corpus-autopublish-v1",
  "targetRepo": "https://github.com/n57d30top/sovryn-open-inventions",
  "targetPath": "results/patch-risk-auditor-v2",
  "commitHash": "fbad1a9d45fa910364c35bc3a8746d0186debbed",
  "pushed": true,
  "pushedAt": "2026-05-04T16:02:29.599Z",
  "dryRun": false,
  "qualityLabel": "good",
  "candidateStatus": "dry_run_ready",
  "releaseReadinessScore": 88,
  "evidenceStrengthScore": 83,
  "reproducibilityScore": 94,
  "publicationSafetyScore": 96,
  "replayCriticalPassRate": 100,
  "securityAuditPassed": true,
  "publicHygienePassed": true,
  "safetyScanPassed": true,
  "reliabilityReplayPassed": true,
  "publicationDryRunPresent": true,
  "noPublicLeaks": true,
  "noCriticalFailures": true,
  "specificityScore": 63,
  "antiTemplateStatus": "needs_revision",
  "disclaimer": "This is an autonomous open-research artifact. It is not a patent filing, patentability opinion, legal novelty opinion, or freedom-to-operate opinion. It was published automatically after automated policy gates and still requires human interpretation before use.",
  "evidenceHash": "eee7f0b57a5a1cebecfbaec128d5faaee7ad47d3852acff48347b47f8945baa8"
}
