{
  "kind": "public_corpus_revision_queue",
  "updatedAt": "2026-05-13T12:51:13.043Z",
  "results": [
    {
      "slug": "corpus-deduplication",
      "title": "Corpus Deduplication for Defensive Publications",
      "lifecycleStatus": "needs_revision",
      "revisionReason": "Falsification status is insufficient_tests."
    },
    {
      "slug": "evidence-chain-v2",
      "title": "Replayable Evidence Chain for Autonomous Research Agents",
      "lifecycleStatus": "needs_revision",
      "revisionReason": "Falsification status is insufficient_tests."
    },
    {
      "slug": "first-discovery-fund-matbench-descriptor-transfer",
      "title": "First Discovery Fund: Matbench Descriptor Transfer External Review Package",
      "lifecycleStatus": "needs_revision",
      "revisionReason": "Quality, candidate status, or anti-template review requires revision."
    },
    {
      "slug": "first-formal-discovery-fund-graph-minor-obstruction-boundary",
      "title": "Public Formal Replay Package: Graph-Minor Obstruction Boundary Candidate",
      "lifecycleStatus": "blocked",
      "revisionReason": "Public hygiene, safety scan, or reliability replay did not pass."
    },
    {
      "slug": "self-built-lab-reproduction-388ccd1946ad",
      "title": "Self-built lab reproduction challenge",
      "lifecycleStatus": "needs_revision",
      "revisionReason": "Specificity score is below the public corpus promotion threshold."
    },
    {
      "slug": "toolchain-policy",
      "title": "Policy-Gated Toolchain Installation Protocol",
      "lifecycleStatus": "needs_revision",
      "revisionReason": "Falsification status is insufficient_tests."
    }
  ],
  "evidenceHash": "4840d56f00d60b7e589d5119d98b1ad96d7a909a0a98c705ba101ece41aa9106"
}
