{
  "kind": "intervention_execution_wave_1_summary",
  "slug": "batch116-intervention-execution-wave-1",
  "title": "Batch 116 Intervention Execution Wave 1",
  "resultKind": "intervention_execution_wave_1",
  "qualityLabel": "good",
  "candidateStatus": "autopublished",
  "lifecycleStatus": "autopublished",
  "releaseReadinessScore": 91,
  "evidenceStrengthScore": 89,
  "reproducibilityScore": 88,
  "publicationSafetyScore": 99,
  "replayCriticalPassRate": 100,
  "specificityScore": 94,
  "antiTemplateStatus": "specific_public_evidence",
  "publicHygienePassed": true,
  "safetyScanPassed": true,
  "reliabilityReplayPassed": true,
  "falsificationStatus": "passes_falsification",
  "baselineComparisonPresent": true,
  "scientificMemoryUpdated": true,
  "scientificQuestion": "Can Required Evidence Field Boundary become a robust external claim-review standard through real external evidence checks?",
  "domain": "extended external field evidence and claim safety v2",
  "limitations": [
    "Bounded safe computational evidence only.",
    "Claim-safety labels are review decisions, not proof.",
    "No external adoption, universal validity, or breakthrough claim is made."
  ],
  "executedInterventionCount": 5,
  "freshExternalClaimArtifactCount": 5,
  "beforeAfterComparisonCount": 5,
  "simpleChecklistBaselineComparisonCount": 5,
  "failedPartialInterventionCount": 2,
  "evidenceHash": "089e03b672187d6ef0224a68798280d616036e60dbc7eec4e94a1441000a76f9"
}
